<!--This is a DXCore settings file-->
<Page Name="CR_FavoriteViews.sln - Favorite Views">
 <Language Name="*Neutral*">
  <Section Name="FaveViews">
   <Option Name="ViewCount" Value="1" />
  </Section>
  <Section Name="SuperView0">
   <Option Name="Name" Value="Core " />
   <Option Name="ActiveFile" Value="C:\Users\Miller-DX\Documents\Visual Studio 2010\Projects\CR_FavoriteViews\CR_FavoriteViews\FavoriteViews.cs" />
   <Option Name="DocViewCount" Value="2" />
  </Section>
  <Section Name="SuperView0.DocView0">
   <Option Name="FileName" Value="C:\Users\Miller-DX\Documents\Visual Studio 2010\Projects\CR_FavoriteViews\CR_FavoriteViews\FavoriteViews.cs" />
   <Option Name="SelectionActive" Value="1520" />
   <Option Name="SelectionAnchor" Value="1520" />
   <Option Name="TopLine" Value="20" />
  </Section>
  <Section Name="SuperView0.DocView1">
   <Option Name="FileName" Value="C:\Users\Miller-DX\Documents\Visual Studio 2010\Projects\CR_FavoriteViews\CR_FavoriteViews\PlugIn1.cs" />
   <Option Name="SelectionActive" Value="270" />
   <Option Name="SelectionAnchor" Value="270" />
   <Option Name="TopLine" Value="1" />
  </Section>
 </Language>
</Page>